Metadata-Version: 2.1
Name: online-store_vafaev
Version: 0.1.0
Summary: Исполняемый пакет для управления пользователями и заказами в онлайн-магазине
Author-email: Vafaev_Elshod <e.vafaev@edu.centraluniversity.ru>
License: MIT
Requires-Python: >=3.8
Requires-Dist: requests>=2.25.1
Requires-Dist: numpy>=1.19.2
